tpml/__init__.py
tpml/gps.py
tpml/metrics.py
tpml/plotters.py
tpml/preprocessing.py
tpml/printers.py
tpml/types.py
tpml-0.1.1.dist-info/METADATA
tpml-0.1.1.dist-info/WHEEL
tpml-0.1.1.dist-info/top_level.txt
tpml-0.1.1.dist-info/RECORD
